{
  "design_id": "boltzgen_r0_s1_config_1",
  "tool": "boltzgen",
  "strategy": "active_site",
  "round": 0,
  "status": "validated",
  "evaluation_stage": "collected",
  "created_at": "2026-02-28T15:32:58.341960+00:00",
  "sequence": "SEIEAAQDLVLSIVKEAYALASSTTEEGLRRARELLEEVRTLAETPVPEAPALTAGAAGALGVILSTFRALALKGNELAKKLVEELNIPESVGAGV",
  "num_residues": 96,
  "rank": 22,
  "source_files": {
    "metrics_csv": "output/boltzgen/r0/s1_active_site/final_ranked_designs/final_designs_metrics_30.csv",
    "structure": "output/boltzgen/r0/s1_active_site/final_ranked_designs/final_30_designs/before_refolding/rank1_config_1.cif"
  },
  "design_metrics": {
    "iptm": 0.69456,
    "min_pae": 2.7304,
    "interaction_pae": 2.7304,
    "interaction_pae_full": 10.43754,
    "ptm": 0.80343,
    "filter_rmsd": 1.95542,
    "plip_hbonds": 10.0,
    "delta_sasa": 2106.29199,
    "helix": 0.76042,
    "sheet": 0.0,
    "loop": 0.23958,
    "num_designed": 96.0,
    "filters_passed": 3.0,
    "quality_score": 1.0,
    "source": "boltzgen"
  },
  "validation": null,
  "scoring": null,
  "composite_score": 0.6969,
  "refolding": {
    "source": "boltzgen_self_consistency",
    "boltzgen_rmsd": 1.95542,
    "boltzgen_plddt": null,
    "boltzgen_iptm": 0.69456,
    "min_interaction_pae": 2.7304
  }
}